macversiontracker-0.8.2.dist-info/licenses/LICENSE
versiontracker/__init__.py
versiontracker/__main__.py
versiontracker/advanced_cache.py
versiontracker/analytics.py
versiontracker/app_finder.py
versiontracker/async_homebrew.py
versiontracker/async_homebrew_prototype.py
versiontracker/async_network.py
versiontracker/benchmarks.py
versiontracker/cache.py
versiontracker/cli.py
versiontracker/config.py
versiontracker/deprecation.py
versiontracker/enhanced_matching.py
versiontracker/error_codes.py
versiontracker/exceptions.py
versiontracker/export.py
versiontracker/homebrew.py
versiontracker/macos_integration.py
versiontracker/menubar_app.py
versiontracker/profiling.py
versiontracker/py.typed
versiontracker/ui.py
versiontracker/utils.py
versiontracker/version.py
versiontracker/version_legacy.py
versiontracker/ai/__init__.py
versiontracker/apps/__init__.py
versiontracker/apps/cache.py
versiontracker/apps/finder.py
versiontracker/apps/matcher.py
versiontracker/commands/__init__.py
versiontracker/commands/list_apps.py
versiontracker/commands/recommendations.py
versiontracker/handlers/__init__.py
versiontracker/handlers/app_handlers.py
versiontracker/handlers/auto_update_handlers.py
versiontracker/handlers/brew_handlers.py
versiontracker/handlers/config_handlers.py
versiontracker/handlers/enhanced_auto_update_handlers.py
versiontracker/handlers/export_handlers.py
versiontracker/handlers/filter_handlers.py
versiontracker/handlers/macos_handlers.py
versiontracker/handlers/outdated_handlers.py
versiontracker/handlers/setup_handlers.py
versiontracker/handlers/ui_handlers.py
versiontracker/handlers/utils_handlers.py
versiontracker/ml/__init__.py
versiontracker/plugins/__init__.py
versiontracker/plugins/example_plugins.py
versiontracker/version/__init__.py
versiontracker/version/comparator.py
versiontracker/version/models.py
versiontracker/version/parser.py
macversiontracker-0.8.2.dist-info/METADATA
macversiontracker-0.8.2.dist-info/WHEEL
macversiontracker-0.8.2.dist-info/entry_points.txt
macversiontracker-0.8.2.dist-info/top_level.txt
macversiontracker-0.8.2.dist-info/RECORD
