Metadata-Version: 2.4
Name: macversiontracker
Version: 0.8.2
Summary: A command-line tool for tracking and managing applications installed outside of the Mac App Store
Author-email: docdyhr <thomas@dyhr.com>
License-Expression: MIT
Project-URL: Homepage, https://github.com/docdyhr/versiontracker
Project-URL: Bug Tracker, https://github.com/docdyhr/versiontracker/issues
Project-URL: Documentation, https://github.com/docdyhr/versiontracker
Project-URL: Source Code, https://github.com/docdyhr/versiontracker
Project-URL: Changelog, https://github.com/docdyhr/versiontracker/blob/master/CHANGELOG.md
Project-URL: PyPI, https://pypi.org/project/macversiontracker/
Keywords: macos,homebrew,version,tracking,updates,cask
Classifier: Development Status :: 4 - Beta
Classifier: Environment :: Console
Classifier: Intended Audience :: System Administrators
Classifier: Intended Audience :: End Users/Desktop
Classifier: Operating System :: MacOS :: MacOS X
Classifier: Programming Language :: Python :: 3
Classifier: Programming Language :: Python :: 3.12
Classifier: Programming Language :: Python :: 3.13
Classifier: Topic :: System :: Software Distribution
Classifier: Topic :: System :: Systems Administration
Classifier: Topic :: Utilities
Requires-Python: >=3.12
License-File: LICENSE
Requires-Dist: pyyaml>=6.0
Requires-Dist: tqdm>=4.65
Requires-Dist: psutil>=5.9
Requires-Dist: tabulate>=0.9.0
Requires-Dist: aiohttp>=3.8.0
Provides-Extra: dev
Requires-Dist: pytest>=7.4; extra == "dev"
Requires-Dist: pytest-cov>=7.0; extra == "dev"
Requires-Dist: pytest-timeout>=2.1; extra == "dev"
Requires-Dist: pytest-mock>=3.11; extra == "dev"
Requires-Dist: pytest-asyncio>=0.21.0; extra == "dev"
Requires-Dist: black>=23.7; extra == "dev"
Requires-Dist: ruff>=0.1; extra == "dev"
Requires-Dist: mypy>=1.5; extra == "dev"
Requires-Dist: types-PyYAML>=6.0; extra == "dev"
Requires-Dist: build>=0.10; extra == "dev"
Requires-Dist: wheel>=0.41; extra == "dev"
Requires-Dist: twine>=4.0; extra == "dev"
Provides-Extra: test
Requires-Dist: pytest>=7.4; extra == "test"
Requires-Dist: pytest-cov>=7.0; extra == "test"
Requires-Dist: pytest-timeout>=2.1; extra == "test"
Requires-Dist: pytest-mock>=3.11; extra == "test"
Requires-Dist: pytest-asyncio>=0.21.0; extra == "test"
Provides-Extra: security
Requires-Dist: bandit[toml]>=1.7; extra == "security"
Requires-Dist: pip-audit>=2.6; extra == "security"
Requires-Dist: safety>=2.3; extra == "security"
Provides-Extra: fuzzy
Requires-Dist: rapidfuzz>=3.0; extra == "fuzzy"
Provides-Extra: ml
Requires-Dist: numpy>=1.24.0; extra == "ml"
Requires-Dist: scikit-learn>=1.3.0; extra == "ml"
Dynamic: license-file
